LICENSE.txt
LICENSES_bundled.txt
MANIFEST.in
Makefile
README.md
pyproject.toml
requirements-dev.txt
setup.cfg
setup.py
demo/benchmark_vs_scipy.py
fast_upfirdn/__init__.py
fast_upfirdn/_scipy_signal.py
fast_upfirdn/_util.py
fast_upfirdn/version.py
fast_upfirdn.egg-info/PKG-INFO
fast_upfirdn.egg-info/SOURCES.txt
fast_upfirdn.egg-info/dependency_links.txt
fast_upfirdn.egg-info/requires.txt
fast_upfirdn.egg-info/top_level.txt
fast_upfirdn/cpu/LICENSE.txt
fast_upfirdn/cpu/__init__.py
fast_upfirdn/cpu/_upfirdn.py
fast_upfirdn/cpu/_upfirdn_apply.c
fast_upfirdn/cpu/_upfirdn_apply.pyx
fast_upfirdn/cupy/__init__.py
fast_upfirdn/cupy/_upfirdn.py
fast_upfirdn/tests/test_upfirdn.py
fast_upfirdn/tests/test_upfirdn_cpu.py