Metadata-Version: 1.2
Name: fast-upfirdn
Version: 0.5
Summary: fast_upfirdn: CPU & GPU implementations of scipy.signal.upfirdn
Home-page: http://github.com/mritools/fast_upfirdn
Author: Gregory R. Lee
Author-email: grlee77@gmail.com
Maintainer: Gregory R. Lee
Maintainer-email: grlee77@gmail.com
License: BSD
Platform: OS Independent
Classifier: Development Status :: 4 - Beta
Classifier: Environment :: Console
Classifier: Intended Audience :: Science/Research
Classifier: License :: OSI Approved :: BSD License
Classifier: Operating System :: OS Independent
Classifier: Programming Language :: Python
Classifier: Topic :: Scientific/Engineering
Requires: numpy
Requires: cython
Requires-Python: >= 3.6
